[
  {
    "id": 1704067200000,
    "content": "Today was absolutely amazing! I finally finished that project I've been working on for weeks. The feeling of accomplishment is incredible. I can't believe how much I've learned through this process.",
    "sentiment": "positive",
    "comment": "Look at you, actually finishing things! The universe is shocked. Keep this energy going!",
    "timestamp": "2024-01-01T10:00:00.000Z"
  },
  {
    "id": 1704153600000,
    "content": "Feeling a bit overwhelmed today. Too many meetings, not enough time to actually get work done. Sometimes I wonder if we're all just pretending to be busy.",
    "sentiment": "negative",
    "comment": "Ah, the classic 'meeting about meetings' syndrome. Your calendar is having an existential crisis.",
    "timestamp": "2024-01-02T14:30:00.000Z"
  },
  {
    "id": 1704240000000,
    "content": "Had coffee with an old friend today. It was nice to catch up, though we didn't talk about anything particularly deep. Just the usual life updates and some laughs.",
    "sentiment": "neutral",
    "comment": "Sometimes the best therapy is just good coffee and better company. Simple but effective.",
    "timestamp": "2024-01-03T16:45:00.000Z"
  },
  {
    "id": 1704326400000,
    "content": "She has proposed me! I can't believe it! This is the happiest day of my life. I never thought this would happen to me.",
    "sentiment": "positive",
    "comment": "Amazing news! So happy for you! 🎉",
    "timestamp": "2024-01-04T12:00:00.000Z"
  },
  {
    "id": 1704412800000,
    "content": "Had a headache today. Couldn't focus on work at all. Hope I feel better tomorrow.",
    "sentiment": "negative",
    "comment": "Hope you feel better soon! 🤗",
    "timestamp": "2024-01-05T09:15:00.000Z"
  },
  {
    "id": 1704499200000,
    "content": "She is not loving me anymore. I don't know what went wrong. This hurts so much.",
    "sentiment": "negative",
    "comment": "Hang in there, you've got this! 🤗",
    "timestamp": "2024-01-06T18:30:00.000Z"
  },
  {
    "id": 1704585600000,
    "content": "Got the job! Finally after months of interviews and rejections. This is a huge step forward in my career.",
    "sentiment": "positive",
    "comment": "This calls for celebration! 🎊",
    "timestamp": "2024-01-07T11:20:00.000Z"
  },
  {
    "id": 1704672000000,
    "content": "Feeling tired today. Need to get more sleep. Work has been exhausting lately.",
    "sentiment": "negative",
    "comment": "Take care of yourself! 💙",
    "timestamp": "2024-01-08T20:45:00.000Z"
  },
  {
    "id": 1704758400000,
    "content": "I love you so much. Every day with you is a blessing. Thank you for being in my life.",
    "sentiment": "positive",
    "comment": "Love this positive energy! ✨",
    "timestamp": "2024-01-09T15:10:00.000Z"
  },
  {
    "id": 1704844800000,
    "content": "Just another day at the office. Nothing special happened. Routine is good sometimes.",
    "sentiment": "neutral",
    "comment": "Thanks for the update! 📋",
    "timestamp": "2024-01-10T13:25:00.000Z"
  }
]
